peji.py
Peji-1.0.2.dist-info/METADATA
Peji-1.0.2.dist-info/WHEEL
Peji-1.0.2.dist-info/entry_points.txt
Peji-1.0.2.dist-info/top_level.txt
Peji-1.0.2.dist-info/RECORD
