Metadata-Version: 2.1
Name: Peji
Version: 1.0.2
Summary: Static site generator.
Home-page: https://peji.gch.icu/
Author: ge
License: UNKNOWN
Platform: UNKNOWN
Classifier: Programming Language :: Python :: 3.9
Classifier: License :: OSI Approved :: The Unlicense (Unlicense)
Classifier: Operating System :: OS Independent
Requires-Python: >=3.6
Requires-Dist: click
Requires-Dist: markdown
Requires-Dist: Jinja2
Requires-Dist: Pygments
Requires-Dist: PyYAML
